newstory_common/__init__.py
newstory_common/models/__init__.py
newstory_common/models/enrichments/__init__.py
newstory_common/models/enrichments/base_enrichment.py
newstory_common/models/enrichments/text_sentiment_enrichment.py
newstory_common/models/entries/__init__.py
newstory_common/models/entries/base_entry.py
newstory_common/models/entries/post_entry.py
newstory_common/models/medias/__init__.py
newstory_common/models/medias/base_media.py
newstory_common/models/medias/image_media.py
newstory_common-1.0.3.dist-info/METADATA
newstory_common-1.0.3.dist-info/WHEEL
newstory_common-1.0.3.dist-info/top_level.txt
newstory_common-1.0.3.dist-info/RECORD
