Metadata-Version: 2.1
Name: newstory-common
Version: 1.0.3
Summary: Common modules for Newstory
Home-page: https://pypi.org/project/newstory_common
Author: Eylon Ronen
Author-email: eylon.ronen@gmail.com
License: MIT
Platform: UNKNOWN
